mfa/__init__.py
mfa/main.py
mfa_authenticator-1.0.4.11.dist-info/METADATA
mfa_authenticator-1.0.4.11.dist-info/WHEEL
mfa_authenticator-1.0.4.11.dist-info/top_level.txt
mfa_authenticator-1.0.4.11.dist-info/RECORD
