Metadata-Version: 2.1
Name: mfa-authenticator
Version: 1.0.4.11
Summary: This helps you setup MFA with 3rd Party Authenticator (Google Authenticator, Microsoft Authenticator, etc)
Author-email: Sunday Ajayi <sunnexajayi@gmail.com>
Project-URL: homepage, https://your_project_homepage.com
Requires-Python: >=3.10
Requires-Dist: python-decouple
Requires-Dist: pyotp
Requires-Dist: qrcode
Requires-Dist: pillow
